docu_ocr/__init__.py
docu_ocr/exceptions.py
docu_ocr/structured.py
docu_ocr_engine-0.1.3.dist-info/METADATA
docu_ocr_engine-0.1.3.dist-info/WHEEL
docu_ocr_engine-0.1.3.dist-info/top_level.txt
docu_ocr_engine-0.1.3.dist-info/RECORD
