Metadata-Version: 2.4
Name: docu-ocr-engine
Version: 0.1.3
Summary: Structured OCR extraction engine
Author-email: Your Name <your@email.com>
Requires-Python: >=3.8
Requires-Dist: fastapi
Requires-Dist: httpx
Requires-Dist: tenacity
Provides-Extra: dev
Requires-Dist: pytest; extra == "dev"
Requires-Dist: flake8; extra == "dev"
Requires-Dist: black; extra == "dev"
Requires-Dist: isort; extra == "dev"
